MediBot/MediBot.bat
MediBot/MediBot.py
MediBot/MediBot_Charges.py
MediBot/MediBot_Crosswalk_Cleaning.py
MediBot/MediBot_Crosswalk_File_Utils.py
MediBot/MediBot_Crosswalk_Library.py
MediBot/MediBot_Crosswalk_Utils.py
MediBot/MediBot_Crosswalk_Validation.py
MediBot/MediBot_Notepad_Utils.py
MediBot/MediBot_Post.py
MediBot/MediBot_Preprocessor.py
MediBot/MediBot_Preprocessor_lib.py
MediBot/MediBot_UI.py
MediBot/MediBot_dataformat_library.py
MediBot/MediBot_debug.bat
MediBot/MediBot_docx_decoder.py
MediBot/MediBot_smart_import.py
MediBot/__init__.py
MediBot/build_deductible_cache.py
MediBot/clear_cache.bat
MediBot/config_editor.bat
MediBot/config_editor.py
MediBot/config_editor_helpers.py
MediBot/crash_diagnostic.bat
MediBot/f_drive_diagnostic.bat
MediBot/full_debug_suite.bat
MediBot/get_medicafe_version.py
MediBot/migrate_browser_downloads.py
MediBot/process_csvs.py
MediBot/update_downloaded_email.py
MediBot/update_json.py
MediBot/update_medicafe.py
MediCafe/MediLink_ConfigLoader.py
MediCafe/__init__.py
MediCafe/__main__.py
MediCafe/api_core.py
MediCafe/api_factory.py
MediCafe/api_hints.py
MediCafe/api_utils.py
MediCafe/core_utils.py
MediCafe/deductible_utils.py
MediCafe/error_reporter.py
MediCafe/gmail_token_service.py
MediCafe/graphql_utils.py
MediCafe/launcher.py
MediCafe/logging_config.py
MediCafe/logging_demo.py
MediCafe/migration_helpers.py
MediCafe/network_route_helpers.py
MediCafe/smart_import.py
MediCafe/submission_index.py
MediLink/InsuranceTypeService.py
MediLink/MediLink_837p_cob_library.py
MediLink/MediLink_837p_encoder.py
MediLink/MediLink_837p_encoder_library.py
MediLink/MediLink_837p_utilities.py
MediLink/MediLink_API_Generator.py
MediLink/MediLink_Azure.py
MediLink/MediLink_Charges.py
MediLink/MediLink_ClaimStatus.py
MediLink/MediLink_DataMgmt.py
MediLink/MediLink_Decoder.py
MediLink/MediLink_Deductible.py
MediLink/MediLink_Deductible_Validator.py
MediLink/MediLink_Deductible_v1_5.py
MediLink/MediLink_Display_Utils.py
MediLink/MediLink_Down.py
medicafe-0.251227.0.dist-info/LICENSE
medicafe-0.251227.0.dist-info/METADATA
medicafe-0.251227.0.dist-info/WHEEL
medicafe-0.251227.0.dist-info/entry_points.txt
medicafe-0.251227.0.dist-info/top_level.txt
medicafe-0.251227.0.dist-info/RECORD
