Metadata-Version: 2.1
Name: medicafe
Version: 0.251227.0
Summary: MediCafe
Home-page: https://github.com/katanada2/MediCafe
Author: Daniel Vidaud
Author-email: daniel@personalizedtransformation.com
License: MIT
Project-URL: Source, https://github.com/katanada2/MediCafe
Project-URL: Bug Tracker, https://github.com/katanada2/MediCafe/issues
Keywords: medicafe medibot medilink medisoft automation healthcare claims
Classifier: Programming Language :: Python :: 3
Classifier: Programming Language :: Python :: 3.4
Classifier: License :: OSI Approved :: MIT License
Classifier: Operating System :: OS Independent
Requires-Python: >=3.4, <3.5
License-File: LICENSE
Requires-Dist: requests ==2.21.0
Requires-Dist: argparse ==1.4.0
Requires-Dist: tqdm ==4.14.0
Requires-Dist: python-docx ==0.8.11
Requires-Dist: PyYAML ==5.2
Requires-Dist: chardet ==3.0.4
Requires-Dist: cffi ==1.8.2
Requires-Dist: msal ==1.26.0
Requires-Dist: numpy ==1.11.3 ; platform_python_implementation != "CPython" or sys_platform != "win32" or python_version > "3.5"
Requires-Dist: pandas ==0.20.0 ; platform_python_implementation != "CPython" or sys_platform != "win32" or python_version > "3.5"
Requires-Dist: lxml ==4.2.0 ; platform_python_implementation != "CPython" or sys_platform != "win32" or python_version > "3.5"
Provides-Extra: binary
Requires-Dist: numpy ==1.11.3 ; (platform_python_implementation == "CPython" and sys_platform == "win32" and python_version <= "3.5") and extra == 'binary'
Requires-Dist: pandas ==0.20.0 ; (platform_python_implementation == "CPython" and sys_platform == "win32" and python_version <= "3.5") and extra == 'binary'
Requires-Dist: lxml ==4.2.0 ; (platform_python_implementation == "CPython" and sys_platform == "win32" and python_version <= "3.5") and extra == 'binary'
